inspector/__init__.py
inspector/app.py
inspector/cli.py
inspector/snipping_tool.py
inspector/static/assets/fonts/BarlowSemiCondensed-Bold.woff2
inspector/static/assets/fonts/BarlowSemiCondensed-BoldItalic.woff2
inspector/static/assets/fonts/BarlowSemiCondensed-Italic.woff2
inspector/static/assets/fonts/BarlowSemiCondensed-Regular.woff2
inspector/static/assets/fonts/BarlowSemiCondensed-SemiBold.woff2
inspector/static/assets/fonts/BarlowSemiCondensed-SemiBoldItalic.woff2
inspector/static/assets/fonts/Inter-Bold.woff2
inspector/static/assets/fonts/Inter-BoldItalic.woff2
inspector/static/assets/fonts/Inter-Italic.woff2
inspector/static/assets/fonts/Inter-Regular.woff2
inspector/static/assets/fonts/JetBrainsMono-Bold-Italic.woff2
inspector/static/assets/fonts/JetBrainsMono-Bold.woff2
inspector/static/assets/fonts/JetBrainsMono-Italic.woff2
inspector/static/assets/fonts/JetBrainsMono-Regular.woff2
inspector/static/assets/fonts/fonts.css
inspector/static/browser.html
inspector/static/browser.js
inspector/static/browser.js.LICENSE.txt
inspector/static/image.html
inspector/static/image.js
inspector/static/image.js.LICENSE.txt
inspector/static/manager.html
inspector/static/manager.js
inspector/static/manager.js.LICENSE.txt
inspector/static/webrecorder.html
inspector/static/webrecorder.js
inspector/static/webrecorder.js.LICENSE.txt
inspector/static/windows.html
inspector/static/windows.js
inspector/static/windows.js.LICENSE.txt
inspector/windows/__init__.py
inspector/windows/base.py
inspector/windows/browser.py
inspector/windows/context.py
inspector/windows/image.py
inspector/windows/manager.py
inspector/windows/web_recorder.py
inspector/windows/windows.py
robocorp_inspector-0.10.3.dist-info/LICENSE
robocorp_inspector-0.10.3.dist-info/METADATA
robocorp_inspector-0.10.3.dist-info/WHEEL
robocorp_inspector-0.10.3.dist-info/entry_points.txt
robocorp_inspector-0.10.3.dist-info/RECORD
