Metadata-Version: 2.1
Name: robocorp-inspector
Version: 0.10.3
Summary: Robocorp Inspector
Home-page: https://github.com/robocorp/inspector
License: Proprietary
Author: Ossi Rajuvaara
Author-email: ossi@rajuvaara.com
Requires-Python: >=3.8,<3.11
Classifier: License :: Other/Proprietary License
Classifier: Programming Language :: Python :: 3
Classifier: Programming Language :: Python :: 3.8
Classifier: Programming Language :: Python :: 3.9
Classifier: Programming Language :: Python :: 3.10
Requires-Dist: clr-loader (>=0.2.7,<0.3.0)
Requires-Dist: importlib-metadata (==4.13.0)
Requires-Dist: mss (==6.1.0)
Requires-Dist: psutil (==5.9.4)
Requires-Dist: pynput-robocorp-fork (==5.0.0)
Requires-Dist: pythonnet (>=3.0.5,<4.0.0)
Requires-Dist: pywebview (==3.7.2)
Requires-Dist: pywin32 (>=302,<304) ; python_full_version != "3.7.6" and python_full_version != "3.8.1" and sys_platform == "win32"
Requires-Dist: requests (==2.28.1)
Requires-Dist: retry (==0.9.2)
Requires-Dist: robocorp-inspector-commons (==0.10.2)
Requires-Dist: rpaframework-core (==11.0.6)
Requires-Dist: rpaframework-recognition (==5.1.2)
Requires-Dist: tk-tools (==0.16.0)
Requires-Dist: types-retry (==0.9.9.2)
Requires-Dist: typing-extensions (==4.4.0)
Requires-Dist: uiautomation (==2.0.16) ; sys_platform == "win32"
Project-URL: Repository, https://github.com/robocorp/inspector
